{
  "required": true,
  "minVersion": "0.8",
  "mixinextras": {
    "minVersion": "0.5.3"
  },
  "package": "meldexun.betterconfig.mixin",
  "compatibilityLevel": "JAVA_8",
  "refmap": "mixins.betterconfig.refmap.json",
  "mixins": [
    "FMLModContainerMixin"
  ],
  "client": [
    "button.ForwardAllMouseEventsMixin",
    "button.GuiListExtendedMixin",
    "button.IGuiListEntryMixin",
    "hover.HoverCheckerMixin",
    "offset.ConfigButtonYOffsetMixin",
    "offset.GuiSlotMixin",
    "FMLClientHandlerMixin",
    "configuration.GuiConfigMixin",
    "configuration.GuiModListMixin"
  ],
  "injectors": {
    "defaultRequire": 1
  }
}